dlds/__init__.py
dlds/dlds_cli.py
dlds/dlds_client.py
dlds/dlds_data_loader.py
dlds/dlds_model.py
dlds/dlds_worker.py
dlds/http_token_authentication.py
dlds/decoder/__init__.py
dlds/decoder/dlds_decoder.py
dlds/decoder/opencv_decoder.py
dlds_client-1.0.0.dist-info/METADATA
dlds_client-1.0.0.dist-info/WHEEL
dlds_client-1.0.0.dist-info/entry_points.txt
dlds_client-1.0.0.dist-info/top_level.txt
dlds_client-1.0.0.dist-info/RECORD
