Metadata-Version: 2.1
Name: dlds-client
Version: 1.0.0
Summary: Python API for Deep Learning DS from Data Spree.
Home-page: UNKNOWN
Author: Eric Dörheit
Author-email: eric.doerheit@data-spree.com
License: UNKNOWN
Platform: UNKNOWN
Requires-Python: >=3.6
Requires-Dist: Click
Requires-Dist: joblib
Requires-Dist: requests
Requires-Dist: tqdm
Provides-Extra: kitti
Requires-Dist: Pillow ; extra == 'kitti'
Provides-Extra: worker
Requires-Dist: aiofiles ; extra == 'worker'
Requires-Dist: aiohttp ; extra == 'worker'
Requires-Dist: aiohttp-cors ; extra == 'worker'
